SerialTool/SerialPy.py
SerialTool/__init__.py
SerialTool-0.1.5.dist-info/DESCRIPTION.rst
SerialTool-0.1.5.dist-info/METADATA
SerialTool-0.1.5.dist-info/RECORD
SerialTool-0.1.5.dist-info/WHEEL
SerialTool-0.1.5.dist-info/entry_points.txt
SerialTool-0.1.5.dist-info/metadata.json
SerialTool-0.1.5.dist-info/top_level.txt
